[
  {
    "id": 1,
    "url": "image-1642725563659.jpg"
  },
  {
    "id": 2,
    "url": "image-1642725635928.jpg"
  },
  {
    "id": 3,
    "url": "image-1642725635930.jpg"
  },
  {
    "id": 4,
    "url": "image-1642725635932.jpg"
  },
  {
    "id": 5,
    "url": "image-1643059626938.jpg"
  },
  {
    "id": 6,
    "url": "image-1643059807882.jpg"
  },
  {
    "id": 7,
    "url": "image-1644447961981.png"
  },
  {
    "id": 8,
    "url": "image-1644448505425.png"
  },
  {
    "id": 9,
    "url": "image-1644448918299.png"
  },
  {
    "id": 10,
    "url": "image-1644448939140.png"
  },
  {
    "id": 11,
    "url": "image-1644449294008.png"
  },
  {
    "id": 12,
    "url": "image-1644449397985.png"
  },
  {
    "id": 13,
    "url": "image-1644449432734.png"
  },
  {
    "id": 14,
    "url": "image-1644451078859.png"
  },
  {
    "id": 15,
    "url": "image-1644451122647.png"
  },
  {
    "id": 16,
    "url": "image-1644451151494.png"
  },
  {
    "id": 17,
    "url": "image-1644451204947.png"
  },
  {
    "id": 18,
    "url": "image-1644456481177.jpg"
  },
  {
    "id": 19,
    "url": "image-1644456532052.jpg"
  },
  {
    "id": 20,
    "url": "image-1644456634993.jpg"
  },
  {
    "id": 21,
    "url": "image-1644457235686.jpg"
  }
]